electricalpy/__init__.py
electricalpy/ckt_solver.py
electricalpy/depev.py
electricalpy/depi.py
electricalpy/depii.py
electricalpy/depiv.py
electricalpy/file.py
electricalpy/indi.py
electricalpy/indiv.py
electricalpy-0.0.26.dist-info/LICENSE.txt
electricalpy-0.0.26.dist-info/METADATA
electricalpy-0.0.26.dist-info/WHEEL
electricalpy-0.0.26.dist-info/top_level.txt
electricalpy-0.0.26.dist-info/RECORD
