Metadata-Version: 2.1
Name: electricalpy
Version: 0.0.26
Summary: Computing and Plotting functions for electrical engineers
Home-page: https://github.com/iam-abdul
Author: ironman 038
Author-email: mohammadabdulrehman739@gmail.com
License: UNKNOWN
Platform: UNKNOWN
Classifier: Programming Language :: Python :: 3
Classifier: License :: OSI Approved :: MIT License
Classifier: Operating System :: OS Independent
Requires-Dist: numpy
Requires-Dist: sympy
Requires-Dist: matplotlib
